[
	{
		"id": 1,
		"priority": 1,
		"action": {"type": "block"},
		"condition": {
			"urlFilter": "gateway.reddit.com/desktopapi/v1/subreddits",
			"resourceTypes": ["xmlhttprequest"]
		}
	},
	{
		"id": 2,
		"priority": 1,
		"action": {"type": "block"},
		"condition": {
			"urlFilter": "gql.reddit.com",
			"resourceTypes": ["xmlhttprequest"]
		}
	},
	{
		"id": 3,
		"priority": 1,
		"action": {"type": "block"},
		"condition": {
			"urlFilter": "reddit.com/svc/shreddit/feeds/all-feed-new",
			"resourceTypes": ["xmlhttprequest"]
		}
	}
]
